funktgtools/__init__.py
funktgtools/admin/__init__.py
funktgtools/admin/admin_funcs.py
funktgtools/admin/constants.py
funktgtools/admin/forwarding.py
funktgtools/admin/poll.py
funktgtools/admin/reactions.py
funktgtools/config/__init__.py
funktgtools/config/config.py
funktgtools/locker/__init__.py
funktgtools/locker/locker.py
funktgtools/markup/__init__.py
funktgtools/markup/markup.py
funktgtools/wallet/__init__.py
funktgtools/wallet/wallet.py
funktgtools-0.1.15.dist-info/METADATA
funktgtools-0.1.15.dist-info/WHEEL
funktgtools-0.1.15.dist-info/top_level.txt
funktgtools-0.1.15.dist-info/RECORD
